{
    "name": "random:random",
    "version": 18,
    "revisions": [
        {
            "revision": 2,
            "global_revision": 1523283651,
            "author": 7504264,
            "stamp": 1722303230,
            "flags": "S",
            "commentary": ""
        },
        {
            "revision": 1,
            "global_revision": 1516353866,
            "author": 8261419,
            "stamp": 1701245919,
            "flags": "A",
            "commentary": "已新增标签：重定向。"
        },
        {
            "revision": 0,
            "global_revision": 1516353864,
            "author": 8261419,
            "stamp": 1701245910,
            "flags": "N",
            "commentary": ""
        }
    ],
    "files": [],
    "page_id": 1451603923,
    "tags": [
        "重定向"
    ],
    "title": "随机页面",
    "sitemap_update": 1722303230000,
    "votings": [],
    "is_locked": true
}