{
    "title": "刪帖公告串-1",
    "id": 15298742,
    "description": "在删除一个页面后，请在此通告。",
    "last": 1777798590,
    "lastUser": 7344601,
    "started": 1665714823,
    "startedUser": 7850356,
    "postsNum": 10,
    "sticky": true,
    "isLocked": false,
    "version": 1,
    "posts": [
        {
            "id": 5638802,
            "title": "刪帖公告串-1",
            "poster": 7850356,
            "stamp": 1665714823,
            "revisions": [],
            "children": []
        },
        {
            "id": 5700358,
            "title": "Re: 刪帖公告串-1",
            "poster": 7850356,
            "stamp": 1667710194,
            "revisions": [],
            "children": []
        },
        {
            "id": 6099535,
            "title": "Re: 刪帖公告串-1",
            "poster": 8049058,
            "stamp": 1685178517,
            "revisions": [],
            "children": []
        },
        {
            "id": 6167451,
            "title": "Re: 刪帖公告串-1",
            "poster": 7850356,
            "stamp": 1691153989,
            "revisions": [],
            "children": []
        },
        {
            "id": 6267726,
            "title": "Re: 刪帖公告串-1",
            "poster": 7504264,
            "stamp": 1702247091,
            "revisions": [],
            "children": []
        },
        {
            "id": 6497889,
            "title": "Re: 刪帖公告串-1",
            "poster": 7967988,
            "stamp": 1714470164,
            "revisions": [],
            "children": []
        },
        {
            "id": 6598146,
            "title": "Re: 刪帖公告串-1",
            "poster": 6818166,
            "stamp": 1723425062,
            "revisions": [],
            "children": []
        },
        {
            "id": 7113779,
            "title": "Re: 刪帖公告串-1",
            "poster": 7344601,
            "stamp": 1755134931,
            "revisions": [],
            "children": []
        },
        {
            "id": 7760054,
            "title": "Re: 刪帖公告串-1",
            "poster": 7344601,
            "stamp": 1775812338,
            "revisions": [],
            "children": []
        },
        {
            "id": 7985934,
            "title": "Re: 刪帖公告串-1",
            "poster": 7344601,
            "stamp": 1777798590,
            "revisions": [],
            "children": []
        }
    ]
}