{
    "title": "爱火燃尽之地 第二幕",
    "id": 17037031,
    "description": "",
    "last": 1740712253,
    "lastUser": 8456860,
    "started": 1739564630,
    "startedUser": null,
    "postsNum": 7,
    "sticky": false,
    "isLocked": false,
    "version": 1,
    "posts": [
        {
            "id": 6813360,
            "title": "bwbb",
            "poster": 6649761,
            "stamp": 1739564709,
            "lastEdit": 1739564725,
            "lastEditBy": 6649761,
            "revisions": [
                {
                    "title": "bwbb",
                    "author": 6649761,
                    "id": 8260806,
                    "stamp": 1739564725
                },
                {
                    "title": "bwbb",
                    "author": 6649761,
                    "id": 8260805,
                    "stamp": 1739564709
                }
            ],
            "children": []
        },
        {
            "id": 6813921,
            "title": "我觉得我玩完了……",
            "poster": 8021906,
            "stamp": 1739624669,
            "lastEdit": 1739624701,
            "lastEditBy": 8021906,
            "revisions": [
                {
                    "title": "我觉得我玩完了……",
                    "author": 8021906,
                    "id": 8261523,
                    "stamp": 1739624701
                },
                {
                    "title": "我觉得我玩完了……",
                    "author": 8021906,
                    "id": 8261522,
                    "stamp": 1739624669
                }
            ],
            "children": [
                {
                    "id": 6814028,
                    "title": "Re: 我觉得我玩完了……",
                    "poster": 6649761,
                    "stamp": 1739633858,
                    "revisions": [],
                    "children": []
                }
            ]
        },
        {
            "id": 6813942,
            "title": "uv",
            "poster": 7594888,
            "stamp": 1739625719,
            "lastEdit": 1739625740,
            "lastEditBy": 7594888,
            "revisions": [
                {
                    "title": "uv",
                    "author": 7594888,
                    "id": 8261548,
                    "stamp": 1739625740
                },
                {
                    "title": "uv",
                    "author": 7594888,
                    "id": 8261545,
                    "stamp": 1739625719
                }
            ],
            "children": [
                {
                    "id": 6814035,
                    "title": "Re: uv",
                    "poster": 6649761,
                    "stamp": 1739633965,
                    "revisions": [],
                    "children": []
                }
            ]
        },
        {
            "id": 6829166,
            "title": "【职员帖】",
            "poster": 8021906,
            "stamp": 1740317384,
            "revisions": [],
            "children": []
        },
        {
            "id": 6837432,
            "title": "这个字体设计很不错",
            "poster": 8456860,
            "stamp": 1740712253,
            "revisions": [],
            "children": []
        }
    ]
}