{
    "title": "琦玉",
    "id": 15333216,
    "description": "",
    "last": 1666854259,
    "lastUser": 7850356,
    "started": 1666787803,
    "startedUser": null,
    "postsNum": 5,
    "sticky": false,
    "isLocked": false,
    "version": 1,
    "posts": [
        {
            "id": 5683012,
            "title": "",
            "poster": 7850356,
            "stamp": 1666788934,
            "revisions": [],
            "children": []
        },
        {
            "id": 5683609,
            "title": "",
            "poster": 8314830,
            "stamp": 1666839675,
            "revisions": [],
            "children": []
        },
        {
            "id": 5683610,
            "title": "",
            "poster": 8314830,
            "stamp": 1666839708,
            "revisions": [],
            "children": [
                {
                    "id": 5683696,
                    "title": "",
                    "poster": 8122538,
                    "stamp": 1666851370,
                    "revisions": [],
                    "children": []
                },
                {
                    "id": 5683739,
                    "title": "",
                    "poster": 7850356,
                    "stamp": 1666854259,
                    "revisions": [],
                    "children": []
                }
            ]
        }
    ]
}